splurge_pub_sub/__init__.py
splurge_pub_sub/__main__.py
splurge_pub_sub/cli.py
splurge_pub_sub/constants.py
splurge_pub_sub/decorators.py
splurge_pub_sub/errors.py
splurge_pub_sub/exceptions.py
splurge_pub_sub/filters.py
splurge_pub_sub/message.py
splurge_pub_sub/pubsub.py
splurge_pub_sub/pubsub_aggregator.py
splurge_pub_sub/pubsub_solo.py
splurge_pub_sub/types.py
splurge_pub_sub/utility.py
splurge_pub_sub/_vendor/splurge_exceptions/__init__.py
splurge_pub_sub/_vendor/splurge_exceptions/__main__.py
splurge_pub_sub/_vendor/splurge_exceptions/cli.py
splurge_pub_sub/_vendor/splurge_exceptions/core/__init__.py
splurge_pub_sub/_vendor/splurge_exceptions/core/base.py
splurge_pub_sub/_vendor/splurge_exceptions/core/exceptions.py
splurge_pub_sub/_vendor/splurge_exceptions/formatting/__init__.py
splurge_pub_sub/_vendor/splurge_exceptions/formatting/message.py
splurge_pub_sub-2025.3.2.dist-info/licenses/LICENSE
splurge_pub_sub-2025.3.2.dist-info/METADATA
splurge_pub_sub-2025.3.2.dist-info/WHEEL
splurge_pub_sub-2025.3.2.dist-info/entry_points.txt
splurge_pub_sub-2025.3.2.dist-info/top_level.txt
splurge_pub_sub-2025.3.2.dist-info/RECORD
