Metadata-Version: 2.4
Name: splurge-pub-sub
Version: 2025.3.2
Summary: A lightweight pub-sub framework.
Author: Jim Schilling
Maintainer: Jim Schilling
License-Expression: MIT
Project-URL: Homepage, https://github.com/jim-schilling/splurge-pub-sub
Project-URL: Repository, https://github.com/jim-schilling/splurge-pub-sub
Project-URL: Documentation, https://github.com/jim-schilling/splurge-pub-sub#readme
Project-URL: Issues, https://github.com/jim-schilling/splurge-pub-sub/issues
Project-URL: Changelog, https://github.com/jim-schilling/splurge-pub-sub/blob/main/CHANGELOG.md
Keywords: splurge,pub-sub
Classifier: Development Status :: 3 - Alpha
Classifier: Intended Audience :: Developers
Classifier: Operating System :: OS Independent
Classifier: Programming Language :: Python :: 3
Classifier: Programming Language :: Python :: 3.10
Classifier: Programming Language :: Python :: 3.11
Classifier: Programming Language :: Python :: 3.12
Classifier: Programming Language :: Python :: 3.13
Classifier: Programming Language :: Python :: 3 :: Only
Classifier: Topic :: Software Development :: Libraries :: Python Modules
Requires-Python: >=3.10
License-File: LICENSE
Provides-Extra: dev
Requires-Dist: pytest>=8.4.1; extra == "dev"
Requires-Dist: pytest-cov>=6.2.1; extra == "dev"
Requires-Dist: pytest-mock>=3.15.1; extra == "dev"
Requires-Dist: hypothesis>=6.97.4; extra == "dev"
Requires-Dist: mypy>=1.18.2; extra == "dev"
Requires-Dist: pre-commit>=4.3.0; extra == "dev"
Requires-Dist: ruff>=0.12.7; extra == "dev"
Provides-Extra: test
Requires-Dist: pytest>=8.4.1; extra == "test"
Requires-Dist: pytest-cov>=6.2.1; extra == "test"
Requires-Dist: pytest-mock>=3.15.1; extra == "test"
Requires-Dist: hypothesis>=6.97.4; extra == "test"
Provides-Extra: lint
Requires-Dist: mypy>=1.18.2; extra == "lint"
Requires-Dist: ruff>=0.12.7; extra == "lint"
Dynamic: license-file
